pyFile/__init__.py
pyFile/file.py
wosPyFile/__init__.py
wosPyFile/file.py
wosPyFile/pyFile.py
wosPyFile-2.0.0.dist-info/LICENSE
wosPyFile-2.0.0.dist-info/METADATA
wosPyFile-2.0.0.dist-info/WHEEL
wosPyFile-2.0.0.dist-info/top_level.txt
wosPyFile-2.0.0.dist-info/RECORD
