Metadata-Version: 2.1
Name: wosPyFile
Version: 2.0.0
Summary: Simple package for file reading
Home-page: https://github.com/WellingtonOSilva/pyFile
Author: Wellington Silva
Author-email: wellington@wosilva.com
License: UNKNOWN
Platform: UNKNOWN
Classifier: Programming Language :: Python :: 3
Classifier: License :: OSI Approved :: MIT License
Classifier: Operating System :: OS Independent
